{
  "fid": 10702,
  "title": "自分の「<<12680>>」の適用中に、「<<12776>>」が融合召喚された場合、「<<12680>>」の効果はどのように適用されますか？",
  "question": "自分の魔法＆罠ゾーンに「<<12680>>」が表側表示で存在し、自分が「<<4837>>」の効果によって、「<<12776>>」を融合召喚しているターンです。\n\nこの場合、「<<12680>>」の『①：自分フィールドの「アンティーク・ギア」モンスターは召喚・特殊召喚されたターンには相手の効果の対象にならず、相手の効果では破壊されない』効果はどのように適用されますか？",
  "answer": "「<<12776>>」は『①：このカードがモンスターゾーンに存在する限り、このカードは魔法・罠カードの効果を受けず、相手はバトルフェイズ中にモンスターの効果を発動できない』モンスター効果を持つモンスターですので、「<<12680>>」の『相手の効果では破壊されない』効果は受けませんが、このターンは『相手の効果の対象にならず』の効果が適用されている状態となりますので、「<<12776>>」は相手のカードの効果の対象になりません。",
  "date": "2017-03-24"
}
