{
  "fid": 10802,
  "title": "自分の墓地の昆虫族モンスターを対象として発動した「<<13495>>」のモンスター効果の処理時に、対象に選択したモンスターの内、1体が墓地に存在しなくなっている場合、処理はどうなりますか？",
  "question": "自分は「<<13495>>」の『②：自分の墓地の昆虫族モンスター３体を対象として発動できる。そのモンスターをデッキに加えてシャッフルする。その後、自分はデッキから１枚ドローする』モンスター効果を発動し、自分の墓地に存在する「<<9895>>」「<<9894>>」「<<9893>>」を対象としました。\n\nその発動にチェーンして、自分が「<<4989>>」を発動し、対象のうちの1体である「<<9894>>」を特殊召喚した場合、効果処理はどうなりますか？",
  "answer": "自分の墓地の昆虫族モンスターを対象として発動した「<<13495>>」のモンスター効果の処理時に、対象に選択したモンスターの内、1体が墓地に存在しなくなっている場合でも、残りの対象のモンスターはデッキに加え、その後のドローの処理も行う事になります。\n\n（質問の状況の場合、「<<9895>>」と「<<9893>>」をデッキに戻してシャッフルし、その後、デッキから1枚ドローする事になります。）",
  "date": "2017-12-01"
}
