{
  "fid": 10929,
  "databaseDate": "2017-03-24",
  "title": "「カラクリ小町 弐弐四」の効果は、「二重召喚」を発動したターン中に適用する場合、どのように効果処理を行いますか？",
  "question": "「カラクリ小町 弐弐四」の効果によって、通常召喚に加えて１度だけ「カラクリ」と名のつくモンスター1体を召喚する事ができるターンにおいて、同一ターン中に「二重召喚」を発動している場合、「二重召喚」による召喚か、「カラクリ小町 弐弐四」の効果による召喚かを相手に伝える必要がありますか？",
  "answer": "1ターンに1度行える通常召喚とは別に、さらに同一ターン中に召喚を行う際には、「二重召喚」と「カラクリ小町 弐弐四」のどちらの効果によるものかを明確にする必要があります。\nしたがって、質問の状況の場合、1ターン中に合計3回の通常召喚が行えます。",
  "tags": [
    "モンスター",
    "魔法"
  ],
  "mentionedCards": [
    7219,
    9501
  ]
}
