{
  "fid": 11011,
  "title": "「マクロコスモス」等の効果が適用中にエクシーズモンスターがフィールド上から離れた場合、エクシーズ素材は墓地へ送られますか？",
  "question": "フィールド上に「<a href=\"faq_search.action?ope=4&cid=6682\">マクロコスモス</a>」や「<a href=\"faq_search.action?ope=4&cid=6695\">閃光の追放者</a>」、「<a href=\"faq_search.action?ope=4&cid=6707\">次元の裂け目</a>」が存在している時に、エクシーズモンスターがフィールド上から離れた場合、フィールド上のエクシーズ素材は墓地へ送られますか？\nそれとも、ゲームから除外されますか？",
  "answer": "フィールド上に「<a href=\"faq_search.action?ope=4&cid=6682\">マクロコスモス</a>」や「<a href=\"faq_search.action?ope=4&cid=6695\">閃光の追放者</a>」が存在している時に、エクシーズモンスターがフィールド上から離れた場合、フィールド上のエクシーズ素材はゲームから除外されます。\nなお、フィールド上に「<a href=\"faq_search.action?ope=4&cid=6707\">次元の裂け目</a>」が存在している時に、エクシーズモンスターがフィールド上から離れた場合、フィールド上のエクシーズ素材は墓地へ送られます。",
  "date": "2017-03-24"
}
