{
  "fid": 11740,
  "title": "「除草獣」と植物族モンスターが同時に破壊された場合、破壊された「除草獣」は墓地から特殊召喚できますか？",
  "question": "フィールド上に存在する「<a href=\"faq_search.action?ope=4&cid=9037\">除草獣</a>」と植物族モンスターが同時に破壊された場合、破壊され墓地へ送られた「<a href=\"faq_search.action?ope=4&cid=9037\">除草獣</a>」自身の効果を発動して墓地から特殊召喚する事はできますか？",
  "answer": "フィールド上に存在する「<a href=\"faq_search.action?ope=4&cid=9037\">除草獣</a>」と植物族モンスターが同時に破壊された場合、破壊され墓地へ送られた「<a href=\"faq_search.action?ope=4&cid=9037\">除草獣</a>」の自身を特殊召喚する効果を発動する事はできません。\nフィールド上に存在する植物族モンスターが破壊された時点で、既に「<a href=\"faq_search.action?ope=4&cid=9037\">除草獣</a>」自身が墓地に存在していなければ、「<a href=\"faq_search.action?ope=4&cid=9037\">除草獣</a>」の効果を発動する事ができません。",
  "date": "2017-03-24"
}
