{
  "fid": 12118,
  "databaseDate": "2017-03-24",
  "title": "「ラーの翼神竜」等のカード名を得た「ファントム･オブ･カオス」をリリースして、「光の創造神ホルアクティ」を特殊召喚できますか？",
  "question": "「オベリスクの巨神兵」「オシリスの天空竜」「ラーの翼神竜」等のカード名を得た「ファントム・オブ・カオス」をフィールド上からリリースして、「光の創造神 ホルアクティ」を特殊召喚する事はできますか？",
  "answer": "「光の創造神 ホルアクティ」を特殊召喚する際に、フィールド上にて「オベリスクの巨神兵」「オシリスの天空竜」「ラーの翼神竜」のカード名を得ている「ファントム・オブ・カオス」をリリースする事はできません。\nしたがって、カードに記載されている元々のカード名が「オシリスの天空竜」「オベリスクの巨神兵」「ラーの翼神竜」となるモンスターをそれぞれ1体ずつリリースしなければなりません。",
  "tags": [
    "モンスター"
  ],
  "mentionedCards": [
    5000
  ]
}
