{
  "fid": 12165,
  "title": "墓地に存在する「<<6588>>」を「<<5118>>」の効果で特殊召喚できますか？",
  "question": "「<<6588>>」を融合素材とした「<<6396>>」や「<<6397>>」に対して「<<5118>>」を発動した場合、「<<6396>>」や「<<6397>>」をエクストラデッキに戻した後、墓地に存在する「<<6588>>」を特殊召喚する事はできますか？\nまた、「<<6390>>」として扱われている「<<7351>>」や「<<6772>>」を融合素材として使用した「<<6396>>」等に対して「<<5118>>」を発動した場合、墓地に存在する「<<7351>>」や「<<6772>>」を特殊召喚する事はできますか？",
  "answer": "融合素材として使用して墓地に送られた「<<6588>>」は、カード名が「<<6390>>」として扱われません。\nしたがって、「<<6396>>」や「<<6397>>」に対して「<<5118>>」を発動しても、墓地に存在する「<<6588>>」を特殊召喚する事はできません。\nまた、「<<6390>>」として扱われている「<<7351>>」や「<<6772>>」を融合素材として使用した「<<6396>>」等に対して「<<5118>>」を発動した場合においても、墓地に存在する「<<7351>>」等を特殊召喚する事はできません。",
  "date": "2017-03-24"
}
