{
  "fid": 12730,
  "databaseDate": "2018-04-12",
  "title": "エクストラモンスターゾーンに自分のモンスターが存在する場合、「閃刀姫－レイ」をリリースしてモンスター効果を発動できますか？",
  "question": "エクストラモンスターゾーンに自分の「リンク・スパイダー」が存在し、自分のメインモンスターゾーンに「閃刀姫－レイ」が表側表示で存在しています。\n\nこの状況で、自分は「閃刀姫－レイ」の『①：このカードをリリースして発動できる。EXデッキから「閃刀姫」モンスター１体をEXモンスターゾーンに特殊召喚する。この効果は相手ターンでも発動できる』モンスター効果を発動する事はできますか？",
  "answer": "「閃刀姫－レイ」の『EXデッキから「閃刀姫」モンスター１体をEXモンスターゾーンに特殊召喚する』モンスター効果は、エクストラモンスターゾーンに特殊召喚を行う効果となりますので、質問の状況のように、エクストラモンスターゾーンに自分のモンスターが既に存在している場合には、「閃刀姫－レイ」の『EXデッキから「閃刀姫」モンスター１体をEXモンスターゾーンに特殊召喚する』モンスター効果を発動する事自体ができません。\n（リンクモンスターのリンクマーカーが指し示す先となるメインモンスターゾーンに特殊召喚する事はできません。）",
  "tags": [
    "リンク"
  ],
  "mentionedCards": [
    13670
  ]
}
