{
  "fid": 130,
  "title": "「無謀な欲張り」を同一ターンに２枚発動した場合、自分のドローフェイズは何回スキップされますか？",
  "question": "「<a href=\"faq_search.action?ope=4&cid=5448\">無謀な欲張り</a>」を同一ターンに2枚発動した場合、『その後、自分のドローフェイズを２回スキップする』処理はどのように適用されますか？",
  "answer": "「<a href=\"faq_search.action?ope=4&cid=5448\">無謀な欲張り</a>」を発動した場合、次の自分のターンのドローフェイズと、その次の自分のターンのドローフェイズの２回がスキップされる事になります。\n\n同一のターンに「<a href=\"faq_search.action?ope=4&cid=5448\">無謀な欲張り</a>」を２枚発動した場合、それぞれの「<a href=\"faq_search.action?ope=4&cid=5448\">無謀な欲張り</a>」の効果が適用され、次の自分のターンのドローフェイズと、その次の自分のターンのドローフェイズの２回がスキップされる事になります。\n\n結果的に、スキップされるドローフェイズは2回となります。",
  "date": "2017-03-24"
}
