{
  "fid": 13019,
  "title": "「神炎竜ルベリオン」の効果や「ギガンティック・スプライト」の②の効果の適用後に「スキルドレイン」を発動した場合、『このターン』や『発動後』と記載された条件を無視することはできますか？",
  "question": "「<a href=\"faq_search.action?ope=4&cid=17070\">神炎竜ルベリオン</a>」の①の効果や「<a href=\"faq_search.action?ope=4&cid=17449\">ギガンティック・スプライト</a>」の②の効果が既に適用されているターンに、「<a href=\"faq_search.action?ope=4&cid=5740\">スキルドレイン</a>」の効果が適用され、「<a href=\"faq_search.action?ope=4&cid=17070\">神炎竜ルベリオン</a>」や「<a href=\"faq_search.action?ope=4&cid=17449\">ギガンティック・スプライト</a>」の効果が無効化されました。\n\nその場合、「<a href=\"faq_search.action?ope=4&cid=17070\">神炎竜ルベリオン</a>」の『このターン、このカードは攻撃できず、自分は融合モンスターしかEXデッキから特殊召喚できない』や、「<a href=\"faq_search.action?ope=4&cid=17449\">ギガンティック・スプライト</a>」の『この効果の発動後、ターン終了時までお互いにレベル２・ランク２・リンク２のモンスターしか特殊召喚できない』を無視することはできますか？",
  "answer": "できません。\n\n「<a href=\"faq_search.action?ope=4&cid=17070\">神炎竜ルベリオン</a>」の『このターン、このカードは攻撃できず、自分は融合モンスターしかEXデッキから特殊召喚できない』や、「<a href=\"faq_search.action?ope=4&cid=17449\">ギガンティック・スプライト</a>」の『この効果の発動後、ターン終了時までお互いにレベル２・ランク２・リンク２のモンスターしか特殊召喚できない』は、これらの効果の処理として適用されます。この処理の適用後にこれらのモンスターの効果が無効化された場合でも、既に適用されている『このターン』や『この効果の発動後』の効果の適用はなくなりません。\n\nなお、「<a href=\"faq_search.action?ope=4&cid=17070\">神炎竜ルベリオン</a>」や「<a href=\"faq_search.action?ope=4&cid=17449\">ギガンティック・スプライト</a>」の効果の発動にチェーンして「<a href=\"faq_search.action?ope=4&cid=5740\">スキルドレイン</a>」を発動し効果を無効にしたのであれば、効果処理そのものが行われませんので、『このターン』や『この効果の発動後』の効果も適用されません。\n\n以下のカードについても同様です。\n\n「<a href=\"faq_search.action?ope=4&cid=10942\">励輝士 ヴェルズビュート</a>」\n「<a href=\"faq_search.action?ope=4&cid=11767\">RR－トリビュート・レイニアス</a>」\n「<a href=\"faq_search.action?ope=4&cid=11907\">占術姫コインノーマ</a>」\n「<a href=\"faq_search.action?ope=4&cid=17418\">丘と芽吹の春化精</a>」\n「<a href=\"faq_search.action?ope=4&cid=16743\">エクソシスター・アソフィール</a>」\n「<a href=\"faq_search.action?ope=4&cid=16741\">エクソシスター・カスピテル</a>」\n「<a href=\"faq_search.action?ope=4&cid=15701\">鉄獣戦線 キット</a>」\n「<a href=\"faq_search.action?ope=4&cid=14944\">捕食植物ヴェルテ・アナコンダ</a>」\n「<a href=\"faq_search.action?ope=4&cid=14489\">海晶乙女コーラルアネモネ</a>」\n「<a href=\"faq_search.action?ope=4&cid=15489\">電脳堺媛－瑞々</a>」\n「<a href=\"faq_search.action?ope=4&cid=11835\">覇王黒竜オッドアイズ・リベリオン・ドラゴン</a>」\n「<a href=\"faq_search.action?ope=4&cid=11764\">キメラテック・ランページ・ドラゴン</a>」",
  "date": "2022-11-19"
}
