{
  "fid": 13071,
  "title": "自身の効果によって攻撃力がアップしている「<<10784>>」に、「<<10623>>」の効果が適用された場合、攻撃力はどうなりますか？",
  "question": "自身の効果によって攻撃力が300ポイントアップしている「<<10784>>」に、「<<10623>>」の効果が適用された場合、攻撃力はどうなりますか？\n\nまた、「<<10623>>」の効果の適用がなくなった場合、攻撃力はどうなりますか？",
  "answer": "「<<10784>>」が自身の効果によって攻撃力が300ポイントアップし、2800になっている状態にて「<<10623>>」の効果が適用された場合、「<<10623>>」の効果が適用されている間は「<<10784>>」の元々の攻撃力（＝2500）の倍の数値、すなわち、5000になります。\n\nその後、「<<10623>>」の効果の適用がなくなった場合、「<<10784>>」の自身の効果によってアップしていた数値は再び適用されず、元々の攻撃力の数値（＝2500）の状態に戻ります。",
  "date": "2017-03-24"
}
