{
  "fid": 13155,
  "title": "「CNo.39 希望皇ホープレイ・ヴィクトリー」が「No.39 希望皇ビヨンド・ザ・ホープ」をエクシーズ素材としている場合、『●』の効果を発動できますか？",
  "question": "「<a href=\"faq_search.action?ope=4&cid=10651\">CNo.39 希望皇ホープレイ・ヴィクトリー</a>」が、「<a href=\"faq_search.action?ope=4&cid=11132\">No.39 希望皇ビヨンド・ザ・ホープ</a>」をエクシーズ素材として持っている場合、『このカードが「希望皇ホープ」と名のついたモンスターをエクシーズ素材としている』事になり、『●このカードが相手の表側表示モンスターに攻撃宣言した時』の効果を発動する事ができますか？",
  "answer": "「<a href=\"faq_search.action?ope=4&cid=11132\">No.39 希望皇ビヨンド・ザ・ホープ</a>」はルール上「希望皇ホープ」としても扱われるため、「<a href=\"faq_search.action?ope=4&cid=10651\">CNo.39 希望皇ホープレイ・ヴィクトリー</a>」が「<a href=\"faq_search.action?ope=4&cid=11132\">No.39 希望皇ビヨンド・ザ・ホープ</a>」をエクシーズ素材として持っている場合、『このカードが「希望皇ホープ」と名のついたモンスターをエクシーズ素材としている』事になります。\n\nしたがって、「<a href=\"faq_search.action?ope=4&cid=10651\">CNo.39 希望皇ホープレイ・ヴィクトリー</a>」は『●このカードが相手の表側表示モンスターに攻撃宣言した時』の効果を発動する事ができます。",
  "date": "2017-03-24"
}
