{
  "fid": 13399,
  "title": "『手札の「ゴーストリック」カード１枚をこのカードの下に重ねてX素材にする』効果処理時に「ゴーストリックの駄天使」自身が裏側守備表示の場合、処理はどうなりますか？",
  "question": "「<a href=\"faq_search.action?ope=4&cid=11422\">ゴーストリックの駄天使</a>」の『②：１ターンに１度、自分メインフェイズに発動できる。手札の「ゴーストリック」カード１枚をこのカードの下に重ねてX素材にする』効果の発動にチェーンして「<a href=\"faq_search.action?ope=4&cid=5432\">月の書</a>」を発動し、「<a href=\"faq_search.action?ope=4&cid=11422\">ゴーストリックの駄天使</a>」が裏側守備表示になった場合、処理はどうなりますか？",
  "answer": "その場合でも、その「<a href=\"faq_search.action?ope=4&cid=11422\">ゴーストリックの駄天使</a>」の下に、手札の「ゴーストリック」と名のついたカードをエクシーズ素材として重ねます。",
  "date": "2017-03-24"
}
