{
  "fid": 13748,
  "title": "「<<11304>>」の効果によって行われるシンクロ召喚を「<<7397>>」の効果や「<<4864>>」で無効にできますか？",
  "question": "「<<11304>>」の効果によって行われるシンクロ召喚を「<<7397>>」の効果や「<<4864>>」で無効にする事はできますか？",
  "answer": "「<<11304>>」の効果は、対象とした墓地のモンスターを特殊召喚する処理が行われた後、ただちにシンクロモンスターのシンクロ召喚を行います。\n\nしたがって、「<<11304>>」の効果の発動にチェーンして「<<4864>>」や「<<7397>>」の効果を発動する事はできませんが、「<<11304>>」の効果処理後に行われるシンクロ召喚の際にチェーン１として「<<4864>>」や「<<7397>>」の効果を発動する事はできます。\n\nなお、「<<4864>>」や「<<7397>>」の効果によってシンクロ召喚が無効になる場合でも、『その時のS素材モンスターは墓地へは行かず除外される』は通常通り適用され、除外されます。",
  "date": "2017-03-24"
}
