{
  "fid": 14048,
  "title": "「影霊衣の降魔鏡」の効果で墓地の「影霊衣の術士 シュリット」を除外した場合、「影霊衣の術士 シュリット」はリリースされた事になりますか？",
  "question": "「<a href=\"faq_search.action?ope=4&cid=11490\">影霊衣の降魔鏡</a>」を発動し、その効果処理にて墓地の「<a href=\"faq_search.action?ope=4&cid=11480\">影霊衣の術士 シュリット</a>」を除外して儀式召喚を行いました。\n\nこの場合、墓地から除外された「<a href=\"faq_search.action?ope=4&cid=11480\">影霊衣の術士 シュリット</a>」はリリースされた事となりますか？\n\nまた、リリースされた事になる場合、『②：このカードが効果でリリースされた場合に発動できる。デッキから戦士族の「影霊衣」儀式モンスター１体を手札に加える』効果を発動する事はできますか？",
  "answer": "「<a href=\"faq_search.action?ope=4&cid=11490\">影霊衣の降魔鏡</a>」の効果処理にて、墓地の「<a href=\"faq_search.action?ope=4&cid=11480\">影霊衣の術士 シュリット</a>」を除外する際に『①：「影霊衣」儀式モンスター１体を儀式召喚する場合、このカード１枚で儀式召喚に必要なレベル分のリリースとして使用できる』効果を適用したとしても、「<a href=\"faq_search.action?ope=4&cid=11480\">影霊衣の術士 シュリット</a>」が除外された事で必要なレベル分のリリースを満たしたものとして儀式召喚が行われるのみで、「<a href=\"faq_search.action?ope=4&cid=11480\">影霊衣の術士 シュリット</a>」自体がリリースされた事にはなりません。\n\nしたがって、質問の状況の場合、「<a href=\"faq_search.action?ope=4&cid=11480\">影霊衣の術士 シュリット</a>」の『②：このカードが効果でリリースされた場合に発動できる。デッキから戦士族の「影霊衣」儀式モンスター１体を手札に加える』効果が発動できるようにはなりません。",
  "date": "2017-03-24"
}
