{
  "fid": 14670,
  "title": "直接攻撃を宣言した相手モンスターに「禁じられた聖槍」の効果が適用されている場合、「星墜つる地に立つ閃珖」を発動できますか？",
  "question": "「<a href=\"faq_search.action?ope=4&cid=11656\">星墜つる地に立つ閃珖</a>」の発動にチェーンして、「<a href=\"faq_search.action?ope=4&cid=9352\">禁じられた聖槍</a>」が発動し、直接攻撃を宣言した相手モンスターが罠カードの効果を受けなくなった場合、処理はどうなりますか？",
  "answer": "「<a href=\"faq_search.action?ope=4&cid=11656\">星墜つる地に立つ閃珖</a>」の発動にチェーンして「<a href=\"faq_search.action?ope=4&cid=9352\">禁じられた聖槍</a>」が発動し、その相手の攻撃モンスターが罠カードの効果を受けなくなった場合、『その攻撃を無効にし』の処理を適用する事ができませんので、『自分はデッキから１枚ドローする』処理も『その後、自分のエクストラデッキ・墓地から「スターダスト」モンスター１体を選んで特殊召喚できる』処理も適用する事ができません。",
  "date": "2017-03-24"
}
