{
  "fid": 14720,
  "title": "相手フィールドにモンスターが存在しない状態で「BF－星影のノートゥング」が特殊召喚された場合も効果は発動しますか？",
  "question": "相手フィールドにモンスターが存在しない状態で、「<a href=\"faq_search.action?ope=4&cid=11649\">BF－星影のノートゥング</a>」が特殊召喚された場合、『①：このカードが特殊召喚に成功した場合に発動する。相手に８００ダメージを与える。その後、相手の表側表示モンスター１体を選び、その攻撃力・守備力を８００ダウンする』効果は発動しますか？",
  "answer": "相手フィールドにモンスターが存在しない場合でも、「<a href=\"faq_search.action?ope=4&cid=11649\">BF－星影のノートゥング</a>」が特殊召喚に成功したのであれば、効果は発動します。\n\nその場合、相手に８００ダメージを与える処理にて処理が完了した扱いとなります。\n（『相手に８００ダメージを与える』処理と『その後、相手の表側表示モンスター１体を選び、その攻撃力・守備力を８００ダウンする』処理は、同時に行われる扱いではありませんので、通常であれば、攻撃力・守備力をダウンした処理にて完了した扱いとなります。）",
  "date": "2017-03-24"
}
