{
  "fid": 14800,
  "title": "「スクランブル・エッグ」は「ロードランナー」が戦闘・効果で破壊された時でなければ発動できませんか？",
  "question": "「<a href=\"faq_search.action?ope=4&cid=11673\">スクランブル・エッグ</a>」は、自分フィールドの「<a href=\"faq_search.action?ope=4&cid=7686\">ロードランナー</a>」が戦闘・効果で破壊された時でなければ発動する事はできませんか？",
  "answer": "「<a href=\"faq_search.action?ope=4&cid=11673\">スクランブル・エッグ</a>」は自分フィールドのモンスターが戦闘・効果によって破壊され墓地へ送られた際に発動する事ができる罠カードになります。\n\nこの効果によって特殊召喚されるのは「<a href=\"faq_search.action?ope=4&cid=7686\">ロードランナー</a>」ですが、破壊された自分フィールドのモンスターが「<a href=\"faq_search.action?ope=4&cid=7686\">ロードランナー</a>」である必要はありません。",
  "date": "2017-03-24"
}
