{
  "fid": 14911,
  "title": "自分フィールドに「インフェルノイド」と名のついたモンスター以外のモンスターが存在する状態でスタンバイフェイズに「<<11748>>」を発動した場合、効果処理は適用されますか？",
  "question": "自分のモンスターゾーンに「インフェルノイド」と名のついたモンスター以外のモンスターが存在している場合、相手のスタンバイフェイズにセットされている「<<11748>>」を発動した場合、『①：相手スタンバイフェイズ毎に、自分の墓地の「インフェルノイド」モンスター１体を対象としてこの効果を発動できる。そのモンスターを手札に加える』効果を適用する事はできますか？\n\nまた、同様に、自分のスタンバイフェイズにセットされている「<<11748>>」を発動した場合、『②：自分スタンバイフェイズ毎に、除外されている自分の「インフェルノイド」モンスター１体を対象としてこの効果を発動できる。そのモンスターを墓地に戻す』効果を適用する事はできますか？",
  "answer": "質問のどちらの状況の場合でも、『③：自分フィールドに「インフェルノイド」モンスター以外のモンスターが存在する場合にこのカードは墓地へ送られる』効果の条件を満たしている状態で、セットされている「<<11748>>」を発動した事になります。\n\n「<<11748>>」のカードの発動と同一のチェーンブロックにて、効果の発動を行っている場合でも、その効果処理が行われる前に『③：自分フィールドに「インフェルノイド」モンスター以外のモンスターが存在する場合にこのカードは墓地へ送られる』処理が適用され「<<11748>>」自身が墓地へ送られる事になります。\n\n結果的に、「<<11748>>」の墓地のモンスターを手札に加える効果・除外されているモンスターを墓地に戻す効果はどちらも適用されません。",
  "date": "2017-03-24"
}
