{
  "fid": 15445,
  "title": "「応戦するG」の墓地にて発動する効果は、自身の効果で特殊召喚されていない場合でも発動できますか？",
  "question": "「<a href=\"faq_search.action?ope=4&cid=11829\">応戦するG</a>」の『③：このカードがフィールドから墓地へ送られた場合に発動できる。デッキから「<a href=\"faq_search.action?ope=4&cid=11829\">応戦するG</a>」以外の攻撃力１５００以下の昆虫族・地属性モンスター１体を手札に加える』効果は、「<a href=\"faq_search.action?ope=4&cid=11829\">応戦するG</a>」が自身の効果によって特殊召喚された後、フィールドから墓地へ送られていなければ発動する事ができませんか？",
  "answer": "「<a href=\"faq_search.action?ope=4&cid=11829\">応戦するG</a>」の『デッキから「<a href=\"faq_search.action?ope=4&cid=11829\">応戦するG</a>」以外の攻撃力１５００以下の昆虫族・地属性モンスター１体を手札に加える』効果は、自身の効果によって特殊召喚されていない場合でも、フィールドから墓地へ送られたのであれば効果を発動する事ができます。\n（通常召喚された後、フィールドから墓地へ送られた場合などでも、効果を発動する事ができます。）",
  "date": "2017-03-24"
}
