{
  "fid": 15673,
  "title": "「<<7397>>」の効果が適用されている場合、「<<11809>>」のペンデュラム効果を発動できますか？",
  "question": "「<<7397>>」の効果が適用されている場合、「<<11809>>」の『①：１ターンに１度、もう片方の自分のPゾーンにカードが存在する場合に発動できる。そのカードを破壊し、そのカードの同名カード１枚をデッキから手札に加える』ペンデュラム効果を発動する事はできますか？\n\nまた、「<<11809>>」の『①：１ターンに１度、もう片方の自分のPゾーンにカードが存在する場合に発動できる。そのカードを破壊し、そのカードの同名カード１枚をデッキから手札に加える』ペンデュラム効果の発動にチェーンして発動した「<<4989>>」の効果によって「<<7397>>」が特殊召喚された場合、処理はどうなりますか？",
  "answer": "「<<7397>>」の効果が適用されている場合、「<<11809>>」のペンデュラム効果を発動する事はできません。\n\nまた、「<<11809>>」のペンデュラム効果の処理時に、「<<7397>>」の効果が適用されている場合には、『そのカードを破壊し』の処理のみを行い、処理を完了する事になります。",
  "date": "2017-03-24"
}
