{
  "fid": 15825,
  "databaseDate": "2017-03-24",
  "title": "自分フィールドにモンスターが存在する場合に、「慧眼の魔術師」のペンデュラム効果によって「時読みの魔術師」を置けますか？",
  "question": "自分フィールドにモンスターが存在する場合、「慧眼の魔術師」の『①：もう片方の自分のPゾーンに「魔術師」カードまたは「EM」カードが存在する場合に発動できる。このカードを破壊し、デッキから「慧眼の魔術師」以外の「魔術師」Pモンスター１体を選び、自分のPゾーンに置く』ペンデュラム効果によって、デッキから「時読みの魔術師」をペンデュラムゾーンに置く事はできますか？",
  "answer": "「時読みの魔術師」はペンデュラムゾーンに魔法カードとして発動する場合には、『自分フィールドにモンスターが存在しない』状態である必要があります。\n\nしかしながら、「慧眼の魔術師」の効果でデッキから選んだペンデュラムモンスターは、ペンデュラムゾーンに魔法カードとして発動してから置かれる扱いではありません。\n\nしたがって、自分フィールドにモンスターが存在する場合であっても、「慧眼の魔術師」のペンデュラム効果によって、デッキから「時読みの魔術師」をペンデュラムゾーンに置く事ができます。",
  "tags": [
    "ペンデュラム"
  ],
  "mentionedCards": [
    11135,
    11784
  ]
}
