{
  "fid": 15963,
  "title": "「コピーキャット」の効果処理時に、自分フィールドに「トゥーン・ワールド」やトゥーンモンスターが存在しなくなった場合、処理はどうなりますか？",
  "question": "自分の魔法＆罠ゾーンに「<a href=\"faq_search.action?ope=4&cid=4798\">トゥーン・ワールド</a>」が表側表示で存在し、自分のモンスターゾーンに「<a href=\"faq_search.action?ope=4&cid=4735\">トゥーン・デーモン</a>」のみが表側表示で存在しています。\n\nその状況で、「<a href=\"faq_search.action?ope=4&cid=4800\">コピーキャット</a>」の発動にチェーンして、相手が「<a href=\"faq_search.action?ope=4&cid=5544\">サンダー・ブレイク</a>」を発動し、「<a href=\"faq_search.action?ope=4&cid=4735\">トゥーン・デーモン</a>」が破壊された場合、処理はどうなりますか？\n\nまた、「<a href=\"faq_search.action?ope=4&cid=4800\">コピーキャット</a>」の発動にチェーンして、相手が「<a href=\"faq_search.action?ope=4&cid=4909\">サイクロン</a>」を発動し、「<a href=\"faq_search.action?ope=4&cid=4798\">トゥーン・ワールド</a>」が破壊された場合、処理はどうなりますか？",
  "answer": "「<a href=\"faq_search.action?ope=4&cid=4800\">コピーキャット</a>」の効果処理時、自分フィールドに「<a href=\"faq_search.action?ope=4&cid=4798\">トゥーン・ワールド</a>」やトゥーンモンスターが存在しなくなっている場合でも、効果処理は通常通り適用されます。\n（『そのカードがモンスターだった場合、そのモンスターを自分フィールドに特殊召喚する』処理、または、『そのカードが魔法・罠カードだった場合、そのカードを自分フィールドにセットする』処理が行われます。）",
  "date": "2017-03-24"
}
