{
  "fid": 16118,
  "databaseDate": "2017-03-24",
  "title": "「トゥーン・ワールド」や「トゥーン・キングダム」の発動が「マジック・ジャマー」で無効になった場合、「トゥーン・マーメイド」等は破壊されますか？",
  "question": "「トゥーン・ワールド」や「トゥーン・キングダム」のカードの発動が「マジック・ジャマー」で無効になり破壊された場合、「トゥーン・マーメイド」等の『④：フィールドの「トゥーン・ワールド」が破壊された時にこのカードは破壊される』効果は適用されますか？",
  "answer": "「マジック・ジャマー」によってカードの発動が無効になり破壊された魔法カードはフィールドで破壊された扱いとはならず、墓地へ送られる事になります。\n\nしたがって、「トゥーン・ワールド」の発動が無効になり破壊された場合でも、「トゥーン・マーメイド」等が自身の効果によって破壊される事はありません。\n（なお、「トゥーン・キングダム」の場合、その発動が無効になり破壊された際には、カード名は「トゥーン・ワールド」として扱われていませんので、「トゥーン・マーメイド」等が自身の効果によって破壊される事はありません。）",
  "tags": [
    "トゥーン"
  ],
  "mentionedCards": [
    4734,
    4798,
    4862,
    11901
  ]
}
