{
  "fid": 16176,
  "title": "「トゥーン・マーメイド」等を墓地から特殊召喚する際に、「トゥーン・ワールド」は自分フィールドに存在する必要はありますか？",
  "question": "自分フィールドに「<a href=\"faq_search.action?ope=4&cid=4798\">トゥーン・ワールド</a>」が表側表示で存在する場合に特殊召喚された「<a href=\"faq_search.action?ope=4&cid=4734\">トゥーン・マーメイド</a>」、「<a href=\"faq_search.action?ope=4&cid=4733\">トゥーン・ドラゴン・エッガー</a>」、「<a href=\"faq_search.action?ope=4&cid=4735\">トゥーン・デーモン</a>」、「<a href=\"faq_search.action?ope=4&cid=4773\">ブルーアイズ・トゥーン・ドラゴン</a>」、「<a href=\"faq_search.action?ope=4&cid=5450\">トゥーン・ブラック・マジシャン・ガール</a>」がその後に破壊される等によって墓地へ送られています。\n\nその「<a href=\"faq_search.action?ope=4&cid=4734\">トゥーン・マーメイド</a>」、「<a href=\"faq_search.action?ope=4&cid=4733\">トゥーン・ドラゴン・エッガー</a>」、「<a href=\"faq_search.action?ope=4&cid=4735\">トゥーン・デーモン</a>」、「<a href=\"faq_search.action?ope=4&cid=4773\">ブルーアイズ・トゥーン・ドラゴン</a>」、「<a href=\"faq_search.action?ope=4&cid=5450\">トゥーン・ブラック・マジシャン・ガール</a>」を「<a href=\"faq_search.action?ope=4&cid=4842\">死者蘇生</a>」の効果で特殊召喚する際に、自分フィールドに「<a href=\"faq_search.action?ope=4&cid=4798\">トゥーン・ワールド</a>」が表側表示で存在している必要はありますか？",
  "answer": "「<a href=\"faq_search.action?ope=4&cid=4734\">トゥーン・マーメイド</a>」等の『自分フィールドに「<a href=\"faq_search.action?ope=4&cid=4798\">トゥーン・ワールド</a>」が存在する場合に特殊召喚できる』は、手札から特殊召喚モンスターを特殊召喚する際の手順となります。\n\n正規の手順によって特殊召喚された後、墓地へ送られている「<a href=\"faq_search.action?ope=4&cid=4734\">トゥーン・マーメイド</a>」等を「<a href=\"faq_search.action?ope=4&cid=4842\">死者蘇生</a>」の効果で墓地から特殊召喚する際には、自分フィールドに「<a href=\"faq_search.action?ope=4&cid=4798\">トゥーン・ワールド</a>」は表側表示で存在している必要はありません。",
  "date": "2017-03-24"
}
