{
  "fid": 16274,
  "title": "「カオス･ソルジャー」を儀式召喚する際に、墓地の「<<12042>>」2体を除外できますか？",
  "question": "「<<4370>>」を儀式召喚する際に、墓地の「<<12042>>」2体の『③：「<<4370>>」モンスターの儀式召喚を行う場合、必要なレベル分のモンスターの内の１体として、墓地のこのカードを除外できる』効果をそれぞれ適用し、除外する事はできますか？",
  "answer": "「<<4676>>」の効果によって「<<4370>>」を儀式召喚する場合、『①：自分の手札・フィールドから、レベルの合計が８以上になるようにモンスターをリリースし、手札から「<<4370>>」を儀式召喚する』事になりますので、墓地の「<<12042>>」2体を除外して、「<<4370>>」を儀式召喚する事ができます。\n\nまた、「<<12000>>」の効果によって「<<4370>>」を儀式召喚する場合、『①：自分の手札・フィールドから、レベルの合計が８になるようにモンスターをリリースし、手札から「<<4370>>」儀式モンスター１体を儀式召喚する』事になりますので、墓地の「<<12042>>」2体を除外して、「<<4370>>」を儀式召喚する事はできません。",
  "date": "2017-03-24"
}
