{
  "fid": 16427,
  "title": "「ライオウ」の効果が適用されている場合、「マジェスペクター・キャット」の効果を発動できますか？",
  "question": "「<a href=\"faq_search.action?ope=4&cid=7397\">ライオウ</a>」の『このカードが自分フィールド上に表側表示で存在する限り、お互いにドロー以外の方法でデッキからカードを手札に加える事はできない』永続効果が適用されている状況で、「<a href=\"faq_search.action?ope=4&cid=11969\">マジェスペクター・キャット</a>」を召喚した時、『①：このカードが召喚・特殊召喚に成功した時に発動できる。このターンのエンドフェイズに、デッキから「マジェスペクター」カード１枚を手札に加える』効果を発動できますか？",
  "answer": "発動できます。\n\nその場合、エンドフェイズにて『デッキから「マジェスペクター」カード１枚を手札に加える』処理を行う際にも「<a href=\"faq_search.action?ope=4&cid=7397\">ライオウ</a>」の効果が適用されているのであれば、デッキからカードを手札に加える処理は行われません。\n\nなお、エンドフェイズに「<a href=\"faq_search.action?ope=4&cid=7397\">ライオウ</a>」の効果が適用されていないのであれば、『デッキから「マジェスペクター」カード１枚を手札に加える』処理は通常通り適用します。\n\n以下の効果の場合も同様です。\n「<a href=\"faq_search.action?ope=4&cid=19162\">ブラック・ホール・ドラゴン</a>」の②\n「<a href=\"faq_search.action?ope=4&cid=8764\">クリスタル・ガール</a>」の①\n「<a href=\"faq_search.action?ope=4&cid=14207\">PSYフレームロード・Λ</a>」の②\n「<a href=\"faq_search.action?ope=4&cid=11996\">昇竜剣士マジェスターP</a>」の①\n「<a href=\"faq_search.action?ope=4&cid=13922\">墓守の異能者</a>」の③\n「<a href=\"faq_search.action?ope=4&cid=12612\">レアメタルフォーゼ・ビスマギア</a>」の①のモンスター効果\n「<a href=\"faq_search.action?ope=4&cid=11871\">魔装戦士 ドラゴディウス</a>」の①のモンスター効果",
  "date": "2023-11-30"
}
