{
  "fid": 16632,
  "title": "「進化する人類」を装備し、元々の攻撃力が変化しているモンスターが「業炎のバリア －ファイヤー・フォース－」の効果で破壊された場合、受けるダメージはどうなりますか？",
  "question": "「<a href=\"faq_search.action?ope=4&cid=7750\">進化する人類</a>」を装備し、元々の攻撃力が2400として扱われている相手の「<a href=\"faq_search.action?ope=4&cid=9863\">アレキサンドライドラゴン</a>」が攻撃した際に、自分は「<a href=\"faq_search.action?ope=4&cid=12022\">業炎のバリア －ファイヤー・フォース－</a>」を発動しました。\n\nこの場合、その「<a href=\"faq_search.action?ope=4&cid=9863\">アレキサンドライドラゴン</a>」が破壊された事で受けるダメージはいくつになりますか？",
  "answer": "質問の状況の場合、「<a href=\"faq_search.action?ope=4&cid=12022\">業炎のバリア －ファイヤー・フォース－</a>」の効果によって破壊されたモンスターに記されている元々の攻撃力の半分のダメージを自分が受ける事になります。\n（質問の状況の場合、「<a href=\"faq_search.action?ope=4&cid=9863\">アレキサンドライドラゴン</a>」の元々の攻撃力2000の半分の1000になります。）\n\nその後、その処理によって受けたダメージと同じ数値分だけ、相手プレイヤーもダメージを受ける事になります。",
  "date": "2017-03-24"
}
