{
  "fid": 16956,
  "title": "「真源の帝王」の効果処理時に、「真源の帝王」が破壊されている場合、処理はどうなりますか？",
  "question": "「<a href=\"faq_search.action?ope=4&cid=12095\">真源の帝王</a>」の『①：１ターンに１度、自分の墓地の「帝王」魔法・罠カード２枚を対象として発動できる。そのカードをデッキに加えてシャッフルする。その後、自分はデッキから１枚ドローする』効果を発動し、自分の墓地の「<a href=\"faq_search.action?ope=4&cid=10993\">始源の帝王</a>」と「<a href=\"faq_search.action?ope=4&cid=10423\">進撃の帝王</a>」を対象として選択しました。\n\nその発動にチェーンして発動した「<a href=\"faq_search.action?ope=4&cid=4909\">サイクロン</a>」の効果によって「<a href=\"faq_search.action?ope=4&cid=12095\">真源の帝王</a>」自身が破壊された場合、「<a href=\"faq_search.action?ope=4&cid=12095\">真源の帝王</a>」の効果の対象となっている2枚のカードはどうなりますか？",
  "answer": "「<a href=\"faq_search.action?ope=4&cid=12095\">真源の帝王</a>」の効果処理時に、効果を発動した「<a href=\"faq_search.action?ope=4&cid=12095\">真源の帝王</a>」自身が破壊された場合には、効果処理は適用されません。\n\n（質問の状況の場合、対象となった「<a href=\"faq_search.action?ope=4&cid=10993\">始源の帝王</a>」と「<a href=\"faq_search.action?ope=4&cid=10423\">進撃の帝王</a>」は墓地に残り、『その後、自分はデッキから１枚ドローする』処理も行われません。）",
  "date": "2017-03-24"
}
