{
  "fid": 17261,
  "databaseDate": "2017-03-24",
  "title": "「破壊剣の使い手－バスター・ブレイダー」が存在する場合、墓地の「破壊剣士の伴竜」の効果を発動できますか？",
  "question": "自分のモンスターゾーンに「破壊剣の使い手－バスター・ブレイダー」のみが存在する場合、「破壊剣士の伴竜」の『③：このカードが墓地に存在し、自分フィールドに「バスター・ブレイダー」が存在する場合、手札から「破壊剣」カード１枚を捨てて発動できる。このカードを墓地から特殊召喚する』効果を発動する事はできますか？",
  "answer": "「破壊剣の使い手－バスター・ブレイダー」は『①：このカードのカード名は、フィールド・墓地に存在する限り「バスター・ブレイダー」として扱う』効果によって、「バスター・ブレイダー」として扱われますので、自分のモンスターゾーンに「破壊剣の使い手－バスター・ブレイダー」のみが存在する場合でも、「破壊剣士の伴竜」の『このカードを墓地から特殊召喚する』効果を発動する事はできます。\n\nなお、「破壊剣の使い手－バスター・ブレイダー」の効果が「禁じられた聖杯」の効果によって無効になり、カード名が「バスター・ブレイダー」として扱われていない状態である場合には、「破壊剣士の伴竜」の『このカードを墓地から特殊召喚する』効果を発動する事はできません。",
  "tags": [
    "モンスター"
  ],
  "mentionedCards": [
    8213,
    12126,
    12127
  ]
}
