{
  "fid": 17290,
  "title": "「リジェクト・リボーン」の効果処理時に、自分のモンスターゾーンの空きが1つになった場合、処理はどうなりますか？",
  "question": "自分のモンスターゾーンに「<a href=\"faq_search.action?ope=4&cid=12060\">レッド・スプリンター</a>」「<a href=\"faq_search.action?ope=4&cid=12061\">レッド・リゾネーター</a>」が存在しています。\n\nこの状況で相手が「<a href=\"faq_search.action?ope=4&cid=5450\">トゥーン・ブラック・マジシャン・ガール</a>」で直接攻撃を宣言した時に、自分が「<a href=\"faq_search.action?ope=4&cid=12179\">リジェクト・リボーン</a>」を発動し、さらにチェーンして「<a href=\"faq_search.action?ope=4&cid=8507\">極限への衝動</a>」を発動した場合、効果処理はどうなりますか？",
  "answer": "質問の状況の場合、チェーン2にて発動した「<a href=\"faq_search.action?ope=4&cid=8507\">極限への衝動</a>」の効果によって、「ソウルトークン」2体が特殊召喚されます。\n\n次にチェーン1に発動した「<a href=\"faq_search.action?ope=4&cid=12179\">リジェクト・リボーン</a>」の効果によって、『バトルフェイズを終了する』処理が行われますが、その際に自分のモンスターゾーンの空きは1つしかありませんので、『その後、自分の墓地からチューナーとSモンスターを１体ずつ選んで特殊召喚できる。この効果で特殊召喚したモンスターの効果は無効化される』処理を行う事はできません。（自分の墓地からはモンスターは1体も特殊召喚されません。）",
  "date": "2017-03-24"
}
