{
  "fid": 17321,
  "title": "除外された「不知火の武士」の効果で、「刀神－不知火」を対象に選択できますか？",
  "question": "「<a href=\"faq_search.action?ope=4&cid=12142\">不知火の武士</a>」の『②：このカードが除外された場合、「<a href=\"faq_search.action?ope=4&cid=12142\">不知火の武士</a>」以外の自分の墓地の「不知火」モンスター１体を対象として発動できる。そのモンスターを手札に加える』効果の対象として、自分の墓地の「<a href=\"faq_search.action?ope=4&cid=12161\">刀神－不知火</a>」を選択する事はできますか？",
  "answer": "「<a href=\"faq_search.action?ope=4&cid=12142\">不知火の武士</a>」の『そのカードを手札に加える』効果の対象として、シンクロモンスターの「<a href=\"faq_search.action?ope=4&cid=12161\">刀神－不知火</a>」を選択する事はできます。\n\nその場合、対象となった「<a href=\"faq_search.action?ope=4&cid=12161\">刀神－不知火</a>」は手札ではなくエクストラデッキに加える事になります。",
  "date": "2017-03-24"
}
