{
  "fid": 17447,
  "title": "「強制転移」の効果によってコントロールが相手に移っている「黄昏の忍者－シンゲツ」が戦闘によって破壊された場合、効果を発動できますか？",
  "question": "「<a href=\"faq_search.action?ope=4&cid=5162\">強制転移</a>」の効果によってコントロールが相手に移っている、元々の持ち主が自分の「<a href=\"faq_search.action?ope=4&cid=12123\">黄昏の忍者－シンゲツ</a>」が戦闘によって破壊され墓地へ送られた場合、『②：このカードが戦闘または相手の効果で破壊され墓地へ送られた場合に発動できる。デッキから「<a href=\"faq_search.action?ope=4&cid=12123\">黄昏の忍者－シンゲツ</a>」以外の「忍者」モンスター１体を手札に加える』効果を発動する事はできますか？",
  "answer": "「<a href=\"faq_search.action?ope=4&cid=5162\">強制転移</a>」の効果によってコントロールが相手に移っている「<a href=\"faq_search.action?ope=4&cid=12123\">黄昏の忍者－シンゲツ</a>」が戦闘によって破壊され自分の墓地へ送られた場合でも、『デッキから「<a href=\"faq_search.action?ope=4&cid=12123\">黄昏の忍者－シンゲツ</a>」以外の「忍者」モンスター１体を手札に加える』効果を発動する事はできます。",
  "date": "2017-03-24"
}
