{
  "fid": 17838,
  "title": "相手フィールドのモンスターを破壊する効果を発動した「青眼の亜白龍」が裏側守備表示になり、表側攻撃表示に戻った場合、「青眼の亜白龍」は攻撃できますか？",
  "question": "「<a href=\"faq_search.action?ope=4&cid=12253\">青眼の亜白龍</a>」の『②：１ターンに１度、相手フィールドのモンスター１体を対象として発動できる。そのモンスターを破壊する。この効果を発動するターン、このカードは攻撃できない』効果を発動しました。\n\nそのターンに発動した「<a href=\"faq_search.action?ope=4&cid=5432\">月の書</a>」の効果によって、その「<a href=\"faq_search.action?ope=4&cid=12253\">青眼の亜白龍</a>」が裏側守備表示になり、同一ターンに「<a href=\"faq_search.action?ope=4&cid=5431\">太陽の書</a>」の効果によって、その「<a href=\"faq_search.action?ope=4&cid=12253\">青眼の亜白龍</a>」が表側攻撃表示に戻った場合、このターンに攻撃を行う事はできますか？",
  "answer": "質問の状況のように、そのターンに効果を発動した「<a href=\"faq_search.action?ope=4&cid=12253\">青眼の亜白龍</a>」が一度裏側守備表示になり、同一ターンに再び表側攻撃表示に戻っているような場合であれば、その「<a href=\"faq_search.action?ope=4&cid=12253\">青眼の亜白龍</a>」はこのターンのバトルフェイズに攻撃を行う事ができます。",
  "date": "2017-03-24"
}
