{
  "fid": 18105,
  "title": "「<<12333>>」の効果処理時に、「竜剣士」と名のついたモンスターや、「竜魔王」と名のついたモンスターがフィールドに存在しなくなった場合、処理はどうなりますか？",
  "question": "自分のモンスターゾーンに「<<11834>>」が表側表示で存在し、相手のモンスターゾーンに「<<12295>>」が表側表示で存在しています。\n\nこの状況で、「<<12333>>」の発動にチェーンして「<<5914>>」が発動し、「<<11834>>」か「<<12295>>」のどちらかがモンスターゾーンに存在しなくなった場合、「<<12333>>」の効果処理はどうなりますか？",
  "answer": "「<<12333>>」の効果処理時に、「竜魔王」と名のついたモンスターや、ペンデュラムモンスター以外の「竜剣士」と名のついたモンスターや、モンスターゾーンに存在しなくなっている場合でも、『お互いのフィールドのカードを全て持ち主のデッキに戻す』処理は通常通り適用されます。\n（『その後、デッキから「竜剣士」モンスターまたは「竜魔王」モンスター１体を召喚条件を無視して特殊召喚できる』処理も適用する事ができます。）",
  "date": "2017-03-24"
}
