{
  "fid": 18135,
  "databaseDate": "2017-03-24",
  "title": "「フォルテッシモ」の効果で融合召喚を行う場合、自分のモンスターゾーンに裏側守備表示で存在するモンスターを融合素材にできますか？",
  "question": "「フォルテッシモ」の『②：魔法＆罠ゾーンの表側表示のこのカードを墓地へ送って発動できる。「幻奏」融合モンスターカードによって決められた融合素材モンスターを自分フィールドから墓地へ送り、その融合モンスター１体をエクストラデッキから融合召喚する』効果で融合召喚を行う場合、自分のモンスターゾーンに裏側守備表示で存在するモンスターを融合素材として墓地へ送る事はできますか？",
  "answer": "「フォルテッシモ」の効果で融合召喚を行う場合、融合召喚する「幻奏」と名のついた融合モンスターによって決められた、正しい融合素材モンスターなのであれば、自分のモンスターゾーンに裏側守備表示で存在するモンスターを融合素材として使用し、墓地へ送る事はできます。",
  "tags": [
    "融合"
  ],
  "mentionedCards": [
    12329
  ]
}
