{
  "fid": 18455,
  "databaseDate": "2017-03-24",
  "title": "自身のモンスター効果によってドラゴン族モンスターを装備している「巨竜の聖騎士」に「禁じられた聖槍」が適用された場合、どうなりますか？",
  "question": "「巨竜の聖騎士」の『①：このカードが召喚・特殊召喚に成功した場合に発動できる。自分の手札・デッキからレベル７・８のドラゴン族モンスター１体を装備カード扱いとしてこのカードに装備する』モンスター効果によって、「フェルグラントドラゴン」が装備カード扱いとして装備されています。\n\nこの状況で「禁じられた聖槍」が発動し、その「巨竜の聖騎士」自身が魔法カードの効果を受けない状態となった場合、適用されている効果はどうなりますか？",
  "answer": "質問の状況のように、自身のモンスター効果によってドラゴン族モンスターを装備している「巨竜の聖騎士」に「禁じられた聖槍」の効果が適用され、魔法カードの効果を受けない状態となった場合でも、装備カードとなっているドラゴン族モンスターは装備されたままとなり、「巨竜の聖騎士」の『②：装備カードを装備したこのカードは他のモンスターの効果を受けない』モンスター効果も適用されたままとなります。",
  "tags": [
    "モンスター"
  ],
  "mentionedCards": [
    7244,
    9352,
    12361
  ]
}
