{
  "fid": 18479,
  "databaseDate": "2017-03-24",
  "title": "墓地に存在する「アークブレイブドラゴン」のモンスター効果は、スタンバイフェイズを迎える度に発動できますか？",
  "question": "墓地に存在する「アークブレイブドラゴン」の『②：このカードが墓地へ送られた次のターンのスタンバイフェイズに、「アークブレイブドラゴン」以外の自分の墓地のレベル７・８のドラゴン族モンスター１体を対象として発動できる。そのモンスターを特殊召喚する』モンスター効果が発動し、その発動が「天罰」によって無効になりました。\n\nその次のターンのスタンバイフェイズにその墓地の「アークブレイブドラゴン」のモンスター効果を発動する事はできますか？",
  "answer": "「アークブレイブドラゴン」の『そのモンスターを特殊召喚する』モンスター効果は、「アークブレイブドラゴン」自身が墓地へ送られた次のターンのスタンバイフェイズにのみ発動する事ができます。\n\nしたがって、その発動が「天罰」によって無効になった場合、その墓地に存在する「アークブレイブドラゴン」のモンスター効果がその次のターンのスタンバイフェイズに再び発動する事はありません。\n\n（ただし、その「アークブレイブドラゴン」が「死者蘇生」の効果によって特殊召喚され再び墓地へ送られた場合などであれば、その墓地へ送られた次のターンのスタンバイフェイズに効果を発動する事ができるようになります。）",
  "tags": [
    "モンスター"
  ],
  "mentionedCards": [
    12359
  ]
}
