{
  "fid": 18594,
  "title": "召喚に成功した「ギャラクシー・ワーム」のモンスター効果で、デッキから同名カードを特殊召喚できますか？",
  "question": "「<a href=\"faq_search.action?ope=4&cid=11926\">ギャラクシー・ワーム</a>」の『①：このカードが召喚に成功した時、自分フィールドにこのカード以外のモンスターが存在しない場合に発動できる。デッキからレベル３以下の「ギャラクシー」効果モンスター１体を特殊召喚する。この効果で特殊召喚したモンスターの効果は無効化される』モンスター効果によって、デッキから同名カードである「<a href=\"faq_search.action?ope=4&cid=11926\">ギャラクシー・ワーム</a>」を特殊召喚する事はできますか？",
  "answer": "「<a href=\"faq_search.action?ope=4&cid=11926\">ギャラクシー・ワーム</a>」もレベル3以下の「ギャラクシー」と名のついた効果モンスターですので、「<a href=\"faq_search.action?ope=4&cid=11926\">ギャラクシー・ワーム</a>」のモンスター効果によってデッキから特殊召喚する事ができます。",
  "date": "2017-03-24"
}
