{
  "fid": 18910,
  "databaseDate": "2017-03-24",
  "title": "デッキから直接墓地へ送られている「トラミッド･スフィンクス」を、「古代遺跡の目覚め」の効果で特殊召喚できますか？",
  "question": "「岩投げアタック」を発動する際のコストや「おろかな埋葬」の効果によってデッキから墓地へ送られた「トラミッド・スフィンクス」を、「古代遺跡の目覚め」の『●自分の墓地の岩石族モンスター１体を対象として発動できる。そのモンスターを守備表示で特殊召喚する』効果によって特殊召喚する事はできますか？",
  "answer": "「トラミッド・スフィンクス」は特殊召喚モンスターですが、自身のモンスター効果に限らず、「トラミッド」と名のついたカードの効果によってであれば、特殊召喚が可能なモンスターとなります。\n\nしたがって、質問の状況のように、デッキから直接墓地へ送られている「トラミッド・スフィンクス」を「古代遺跡の目覚め」の効果によって、墓地から特殊召喚する事はできます。",
  "tags": [
    "モンスター"
  ],
  "mentionedCards": [
    5236,
    6362,
    12429,
    12473
  ]
}
