{
  "fid": 18961,
  "title": "手札からの特殊召喚に成功した「<<12412>>」のモンスター効果の適用後に、「<<12412>>」が破壊された場合、特殊召喚されている「朧影トークン」はどうなりますか？",
  "question": "自分の「<<12412>>」の『①：このカードが手札からの特殊召喚に成功した時に発動できる。自分フィールドに「朧影トークン」（鳥獣族・闇・星１・攻／守０）２体を特殊召喚する。このトークンはリリースできず、S素材にできない』モンスター効果を発動しているターンです。\n\nこの状況で「<<12412>>」が相手の発動した「<<5544>>」によって破壊され、フィールドに存在しなくなった場合、特殊召喚されている「朧影トークン」はどうなりますか？",
  "answer": "「<<12412>>」のモンスター効果によって特殊召喚されている「朧影トークン」は、「<<12412>>」がその後に破壊されフィールドに存在しなくなった場合でも、モンスターゾーンに残ります。（「<<12412>>」が破壊された事によって破壊される事はありません。）\n\nなお、「<<12412>>」がフィールドに存在しなくなった場合でも、その特殊召喚されている「朧影トークン」には、『このトークンはリリースできず、S素材にできない』効果が適用されたままですので、リリースする事はできず、シンクロ素材として使用する事もできません。",
  "date": "2017-03-24"
}
