{
  "fid": 19385,
  "databaseDate": "2018-05-17",
  "title": "「ダーク・サンクチュアリ」が破壊された場合、通常モンスター扱いとしてモンスターゾーンに存在する「死のメッセージ「A」」はどうなりますか？",
  "question": "自分のフィールドゾーンに「ダーク・サンクチュアリ」が表側表示で存在し、自分の魔法＆罠ゾーンに表側表示で存在する「ウィジャ盤」の『①：相手エンドフェイズにこの効果を発動する。手札・デッキから、「死のメッセージ」カード１枚を「E」「A」「T」「H」の順番で自分の魔法＆罠ゾーンに出す』効果が発動しました。\n\nその際に、「ダーク・サンクチュアリ」の『①：自分の「ウィジャ盤」の効果で「死のメッセージ」カードを出す場合、そのカードを通常モンスター（悪魔族・闇・星１・攻／守０）として特殊召喚できる。この効果で特殊召喚したカードは「ウィジャ盤」以外のカードの効果を受けず、攻撃対象にされない（この効果が適用されたモンスターしか自分フィールドに存在しない状態での相手の攻撃は自分への直接攻撃になる）』効果を適用し、「死のメッセージ「A」」を通常モンスター扱いとして特殊召喚しています。\n\nその後、「サイクロン」が発動し、「ダーク・サンクチュアリ」が破壊された場合、通常モンスター扱いとしてモンスターゾーンに存在する「死のメッセージ「A」」はどうなりますか？",
  "answer": "質問の状況のように、「ダーク・サンクチュアリ」の効果によって通常モンスター扱いとなっている「死のメッセージ「A」」は、その後に「サイクロン」が発動し、「ダーク・サンクチュアリ」が破壊されたとしても、通常モンスター扱いとしてそのままモンスターゾーンに残る事になります。\n\nなお、その場合でも、「死のメッセージ「A」」は、『この効果で特殊召喚したカードは「ウィジャ盤」以外のカードの効果を受けず、攻撃対象にされない（この効果が適用されたモンスターしか自分フィールドに存在しない状態での相手の攻撃は自分への直接攻撃になる）』効果が適用されたままの状態となります。",
  "tags": [
    "通常モンスター・トークン"
  ],
  "mentionedCards": [
    4909,
    5224,
    5272,
    12572
  ]
}
