{
  "fid": 19469,
  "databaseDate": "2017-03-24",
  "title": "「スクランブル・ユニオン」の効果の対象としたモンスター3体のうち、1体が除外されていない場合、処理はどうなりますか？",
  "question": "「スクランブル・ユニオン」の『①：除外されている自分の機械族・光属性の、通常モンスターまたはユニオンモンスターを３体まで対象として発動できる。そのモンスターを特殊召喚する』効果を発動し、対象として「A－アサルト・コア」、「B－バスター・ドレイク」、「C－クラッシュ・ワイバーン」の3体が選択されました。\n\nその発動にチェーンして相手が「異次元からの埋葬」を発動し、「A－アサルト・コア」を墓地に戻した場合、効果処理はどうなりますか？",
  "answer": "質問の状況のように、2体以上のモンスターを対象として発動した「スクランブル・ユニオン」の効果処理時に、対象のうち1体が除外されていない状態となる場合でも、残りの対象のモンスターを特殊召喚する処理は行われます。\n\n（質問の状況の場合、残りの対象となる「B－バスター・ドレイク」と「C－クラッシュ・ワイバーン」は特殊召喚される事になります。）",
  "tags": [
    "ユニオン"
  ],
  "mentionedCards": [
    6941,
    12582,
    12583,
    12584,
    12588
  ]
}
