{
  "fid": 20023,
  "databaseDate": "2017-03-24",
  "title": "「降竜の魔術師」2体を素材として、モンスターを融合・シンクロ・エクシーズ召喚した場合、その得た効果によって攻撃力はどうなりますか？",
  "question": "自分のモンスターゾーンに存在する「降竜の魔術師」2体を素材として「スターヴ・ヴェノム・フュージョン・ドラゴン」を融合召喚しました。\n\nこの場合、『●このカードがドラゴン族モンスターと戦闘を行うダメージステップの間、このカードの攻撃力は元々の攻撃力の倍になる』効果はどのように適用されますか？",
  "answer": "「降竜の魔術師」2体を素材として、モンスターを融合・シンクロ・エクシーズ召喚した場合でも、『このカードの攻撃力は元々の攻撃力の倍になる』効果によって倍になった攻撃力は元々の攻撃力としては扱いませんので、結果的に、「降竜の魔術師」1体のみを素材に含めてモンスターを融合・シンクロ・エクシーズ召喚した場合と、攻撃力の数値は変わりません。\n（質問の状況の場合、「スターヴ・ヴェノム・フュージョン・ドラゴン」の攻撃力は、ドラゴン族モンスターと戦闘を行うダメージステップの間、元々の攻撃力2800の倍である5600の状態になります。）",
  "tags": [
    "モンスター"
  ],
  "mentionedCards": [
    12628,
    12736
  ]
}
