{
  "fid": 20124,
  "title": "自分または相手のモンスターゾーンに「不意打ち又佐」が存在する場合、「スウィッチヒーロー」を発動できますか？",
  "question": "自分または相手のモンスターゾーンに「<a href=\"faq_search.action?ope=4&cid=5898\">不意打ち又佐</a>」が存在する場合、「<a href=\"faq_search.action?ope=4&cid=12814\">スウィッチヒーロー</a>」の『①：お互いのフィールドのモンスターの数が同じ場合、そのモンスターのコントロールを全て入れ替える』効果を発動する事はできますか？",
  "answer": "「<a href=\"faq_search.action?ope=4&cid=12814\">スウィッチヒーロー</a>」の効果は、お互いのモンスターゾーンのモンスター全てのコントロールを入れ替える効果となりますので、『このカードは表側表示でフィールド上に存在する限り、コントロールを変更する事はできない』モンスター効果を持つ「<a href=\"faq_search.action?ope=4&cid=5898\">不意打ち又佐</a>」が、自分または、相手のモンスターゾーンに表側表示で存在する場合には、「<a href=\"faq_search.action?ope=4&cid=12814\">スウィッチヒーロー</a>」を発動する事自体ができません。",
  "date": "2017-03-24"
}
