{
  "fid": 20406,
  "title": "「<<12905>>」を装備したモンスターが裏側守備表示になった場合や、戦闘で破壊された場合、「<<12905>>」の効果によって自分はダメージを受けますか？",
  "question": "「<<12905>>」を装備している「<<6845>>」が、その後に発動した「<<5432>>」の効果によって裏側守備表示になった場合、「<<12905>>」の『④：魔法＆罠ゾーンの表側表示のこのカードがフィールドから離れた時に自分は３０００ダメージを受ける』効果は適用されますか？\n\nまた、「<<12905>>」を装備している「<<6845>>」が戦闘によって破壊され墓地へ送られた場合、「<<12905>>」の『④：魔法＆罠ゾーンの表側表示のこのカードがフィールドから離れた時に自分は３０００ダメージを受ける』効果は適用されますか？",
  "answer": "質問の状況のように、装備モンスターが裏側守備表示になった場合や、装備モンスターが戦闘で破壊された場合、対象を失った「<<12905>>」は破壊され墓地へ送られる事になります。\n\nこの場合、「<<12905>>」の効果は適用され、自分は3000のダメージを受けます。",
  "date": "2017-03-24"
}
