{
  "fid": 21348,
  "databaseDate": "2022-12-30",
  "title": "このターンに融合召喚された融合モンスターがフィールドに存在しなくなっている場合、エンドフェイズに「融合再生機構」の効果を発動できますか？",
  "question": "自分が発動した「融合」の効果によって「サンダー・ドラゴン」2体を融合素材として墓地へ送り、「双頭の雷龍」を融合召喚した際に、相手が「激流葬」を発動した事で、融合召喚に成功したその「双頭の雷龍」は破壊され墓地へ送られました。\n\nこのターンのエンドフェイズに自分は「融合再生機構」の『②：自分・相手のエンドフェイズに、このターン融合召喚に使用した自分の墓地の融合素材モンスター１体を対象として発動できる。そのモンスターを手札に加える』効果を発動する事はできますか？",
  "answer": "質問の状況のように、このターンに融合素材としてモンスターを墓地へ送り、融合召喚に成功したモンスターが、エンドフェイズを迎える前にフィールドに存在しなくなっているような場合でも、このターンに融合素材に使用したモンスター（＝質問の状況の場合、「サンダー・ドラゴン」）が自分の墓地に存在しているのであれば、このターンのエンドフェイズに「融合再生機構」の効果を発動する事ができます。",
  "tags": [
    "魔法"
  ],
  "mentionedCards": [
    12872
  ]
}
