{
  "fid": 21937,
  "databaseDate": "2022-12-30",
  "title": "「魔界劇団－メロー・マドンナ」ペンデュラム効果の発動にチェーンして、「サイクロン」が発動し、「魔界劇団－メロー・マドンナ」自身が破壊された場合、処理はどうなりますか？",
  "question": "自分が「魔界劇団－メロー・マドンナ」の『①：１０００LPを払って発動できる。デッキから「魔界劇団－メロー・マドンナ」以外の「魔界劇団」Pモンスター１体を手札に加える。この効果の発動後、ターン終了時まで自分は「魔界劇団」Pモンスターしか特殊召喚できない』ペンデュラム効果を発動した際に、相手がチェーンして「サイクロン」を発動し、ペンデュラムゾーンの「魔界劇団－メロー・マドンナ」が破壊されました。\n\nこの場合、効果処理はどうなりますか？",
  "answer": "「魔界劇団－メロー・マドンナ」ペンデュラム効果の発動にチェーンして、「サイクロン」が発動し、「魔界劇団－メロー・マドンナ」自身が破壊された場合、『デッキから「魔界劇団－メロー・マドンナ」以外の「魔界劇団」Pモンスター１体を手札に加える』処理は適用されず、『この効果の発動後、ターン終了時まで自分は「魔界劇団」Pモンスターしか特殊召喚できない』処理も適用されません。",
  "tags": [
    "ペンデュラム"
  ],
  "mentionedCards": [
    4909,
    13862
  ]
}
