{
  "fid": 22074,
  "title": "「<<14017>>」の処理によって、裏側守備表示の「<<14014>>」をリリースして儀式召喚した場合、フィールドのカードを破壊する処理は適用できますか？",
  "question": "自分のモンスターゾーンに裏側守備表示の「<<14014>>」が存在しています。\n\nこの状況で、自分は「<<14017>>」を発動し、その裏側守備表示で存在する「<<14014>>」をリリースして儀式召喚を行った場合、『「<<14013>>」または「<<14014>>」をリリースして儀式召喚した場合には、さらにフィールドのカード１枚を選んで破壊できる』処理を適用する事はできますか？",
  "answer": "質問の状況のように、「<<14017>>」の処理によって、自分のモンスターゾーンに裏側守備表示の「<<14014>>」をリリースして儀式召喚を行った場合でも、『「<<14013>>」または「<<14014>>」をリリースして儀式召喚した場合には、さらにフィールドのカード１枚を選んで破壊できる』処理を適用する事ができます。",
  "date": "2018-08-03"
}
