{
  "fid": 22403,
  "databaseDate": "2020-02-24",
  "title": "「真超量機神王ブラスター・マグナ」の『②』のモンスター効果の処理時に、そのエクシーズモンスターの同名カードが自分のモンスターゾーンに存在している場合、処理はどうなりますか？",
  "question": "エクストラモンスターゾーンに自分の「真超量機神王ブラスター・マグナ」が存在し、そのリンク先となる自分のメインモンスターゾーンに、「超量機獣ラスターレックス」をエクストラデッキから特殊召喚しました。\n\nこの時発動する、「真超量機神王ブラスター・マグナ」の『②』のモンスター効果の発動にチェーンして、自分が「リビングデッドの呼び声」を発動し、「超量機獣ラスターレックス」を墓地から特殊召喚した場合、自分はドローする処理を行えなくなりますか？",
  "answer": "質問の状況のように、「真超量機神王ブラスター・マグナ」の『②』のモンスター効果の発動のきっかけとなった、「超量」と名のついたエクシーズモンスターと同名のモンスターが、効果処理時に自分のモンスターゾーンに表側表示で存在している場合でも、『自分はデッキから１枚ドローする』処理は通常通り適用されます。",
  "tags": [
    "リンク"
  ],
  "mentionedCards": [
    4989,
    14287,
    14296
  ]
}
