{
  "fid": 22435,
  "title": "「マクロコスモス」の適用中に、「方界法」の効果を発動できますか？",
  "question": "相手の魔法＆罠ゾーンに「<a href=\"faq_search.action?ope=4&cid=6682\">マクロコスモス</a>」が表側表示で存在し、『②：このカードが魔法＆罠ゾーンに存在する限り、墓地へ送られるカードは墓地へは行かず除外される』効果が適用されています。\n\nこの状況で、自分は「<a href=\"faq_search.action?ope=4&cid=14381\">方界法</a>」の『①：自分メインフェイズに発動できる。手札から「方界」カード１枚を墓地へ送り、自分はデッキから１枚ドローする』効果を発動する事はできますか？",
  "answer": "「<a href=\"faq_search.action?ope=4&cid=6682\">マクロコスモス</a>」の効果が適用されている場合でも、「<a href=\"faq_search.action?ope=4&cid=14381\">方界法</a>」の『手札から「方界」カード１枚を墓地へ送り、自分はデッキから１枚ドローする』効果を発動する事はできます。\n\nその場合、手札から選んだ「方界」と名のついたカードは、「<a href=\"faq_search.action?ope=4&cid=6682\">マクロコスモス</a>」の効果によって墓地へは送られず除外されますので、『自分はデッキから１枚ドローする』処理は適用されません。",
  "date": "2022-12-30"
}
