{
  "fid": 22512,
  "databaseDate": "2022-12-30",
  "title": "ペンデュラム召喚によって「魔導耀士 デイブレイカー」のリンク先に2体の魔法使い族モンスターが特殊召喚された場合、魔力カウンターはいくつ置かれますか？",
  "question": "エクストラモンスターゾーンに自分の「魔導耀士 デイブレイカー」が存在し、ペンデュラム召喚によって、エクストラデッキから「マギステル・オブ・エンディミオン」と「サーヴァント・オブ・エンディミオン」が特殊召喚されました。\n\nこの場合、「魔導耀士 デイブレイカー」の『②：このカードのリンク先に魔法使い族モンスターが特殊召喚された場合に発動する。このカードに魔力カウンターを１つ置く』モンスター効果の発動と処理はどうなりますか？",
  "answer": "質問の状況のように、「魔導耀士 デイブレイカー」のリンク先となる2ヵ所のメインモンスターゾーンに2体の魔法使い族モンスターが同時に特殊召喚された場合でも、『このカードに魔力カウンターを１つ置く』モンスター効果は1度のみ発動し、置かれる魔力カウンターの数も1つのみとなります。",
  "tags": [
    "リンク"
  ],
  "mentionedCards": [
    14441,
    14442,
    14445
  ]
}
