{
  "fid": 23019,
  "title": "「根絶の機皇神」の『②』の効果によって破壊するシンクロモンスターに、攻撃力が０の「ワンショット・キャノン」を選べますか？",
  "question": "「<a href=\"faq_search.action?ope=4&cid=15343\">根絶の機皇神</a>」の『②』の効果によって破壊するシンクロモンスターに、攻撃力が０の「<a href=\"faq_search.action?ope=4&cid=8331\">ワンショット・キャノン</a>」を選ぶ事はできますか？",
  "answer": "「<a href=\"faq_search.action?ope=4&cid=15343\">根絶の機皇神</a>」の『②』の効果によって破壊するシンクロモンスターに攻撃力が０のモンスターである「<a href=\"faq_search.action?ope=4&cid=8331\">ワンショット・キャノン</a>」等を選ぶ事はできます。\n\nその場合、選んだ「<a href=\"faq_search.action?ope=4&cid=8331\">ワンショット・キャノン</a>」は破壊されますが、結果的に相手が受けるダメージは０になります。",
  "date": "2020-05-29"
}
