{
  "fid": 23416,
  "title": "「マクロコスモス」や「ディメンション・アトラクター」の適用中に、「アーティファクト－ロンギヌス」の『このターン、お互いにカードを除外できない』効果を発動できますか？",
  "question": "「<a href=\"faq_search.action?ope=4&cid=6682\">マクロコスモス</a>」や「<a href=\"faq_search.action?ope=4&cid=14740\">ディメンション・アトラクター</a>」の効果の適用中に、「<a href=\"faq_search.action?ope=4&cid=11243\">アーティファクト－ロンギヌス</a>」の『③』の『手札または自分フィールドのこのカードをリリースして発動できる。このターン、お互いにカードを除外できない』効果を発動できますか？",
  "answer": "「<a href=\"faq_search.action?ope=4&cid=6682\">マクロコスモス</a>」や「<a href=\"faq_search.action?ope=4&cid=14740\">ディメンション・アトラクター</a>」の効果が適用され、墓地へ送られるカードが除外される場合でも、「<a href=\"faq_search.action?ope=4&cid=11243\">アーティファクト－ロンギヌス</a>」の『③』の効果を発動できます。\n\nその場合、効果を発動する際のコストとしてリリースされる「<a href=\"faq_search.action?ope=4&cid=11243\">アーティファクト－ロンギヌス</a>」は除外され、効果の適用以降、『このターン、お互いにカードを除外できない』効果が適用されます。 \n\nなお、「<a href=\"faq_search.action?ope=4&cid=14740\">ディメンション・アトラクター</a>」と「<a href=\"faq_search.action?ope=4&cid=11243\">アーティファクト－ロンギヌス</a>」の効果を同一ターン中に発動・適用した場合、そのターンは「<a href=\"faq_search.action?ope=4&cid=11243\">アーティファクト－ロンギヌス</a>」の効果によりカードを除外できなくなり、次のターンは「<a href=\"faq_search.action?ope=4&cid=14740\">ディメンション・アトラクター</a>」の効果により墓地へ送られるカードは除外されることになります。",
  "date": "2021-11-06"
}
