{
  "fid": 23656,
  "title": "「赤しゃりの軍貫」を素材として「弩級軍貫－いくら型一番艦」をX召喚した場合、『①』の『●「しゃりの軍貫」』の処理を適用できますか？",
  "question": "「<a href=\"faq_search.action?ope=4&cid=17428\">赤しゃりの軍貫</a>」をエクシーズ素材として、「<a href=\"faq_search.action?ope=4&cid=16232\">弩級軍貫－いくら型一番艦</a>」をエクシーズ召喚した場合、「<a href=\"faq_search.action?ope=4&cid=16232\">弩級軍貫－いくら型一番艦</a>」の『①』の効果を発動し、『●「<a href=\"faq_search.action?ope=4&cid=16200\">しゃりの軍貫</a>」：自分はデッキから１枚ドローする』効果を適用できますか？",
  "answer": "モンスターゾーンで『①：このカードのカード名は、手札・デッキ・フィールド・墓地に存在する限り「<a href=\"faq_search.action?ope=4&cid=16200\">しゃりの軍貫</a>」として扱う』効果が適用されている「<a href=\"faq_search.action?ope=4&cid=17428\">赤しゃりの軍貫</a>」をエクシーズ召喚の素材としたのであれば、『●「<a href=\"faq_search.action?ope=4&cid=16200\">しゃりの軍貫</a>」』の処理を適用できます。",
  "date": "2022-05-02"
}
