{
  "fid": 24328,
  "databaseDate": "2026-07-23",
  "title": "「黒き混沌の魔術師ブラック・カオス」を対象に「超逸融合」を発動した場合、融合召喚できますか？",
  "question": "『このカードを対象とする効果以外の相手が発動した効果を受けない』効果が適用されている「黒き混沌の魔術師ブラック・カオス」を対象として「超逸融合」を発動した場合、『そのモンスターとはレベルが異なり、種族・属性が同じモンスター１体をEXデッキから効果を無効にして特殊召喚する』処理によって魔法使い族・闇属性モンスターを特殊召喚した後、『●この効果で特殊召喚したモンスターと対象のモンスターを融合素材とし、融合モンスター１体を融合召喚する』効果を選んで融合召喚できますか？",
  "answer": "できます。\n\n「黒き混沌の魔術師ブラック・カオス」は自身を対象として発動した効果は受けますので、「超逸融合」の効果で融合召喚の素材にできます。\n\n以下のモンスターを対象として「超逸融合」を発動し、１つ目の『●』の効果を適用する場合も同様に、テキスト通りに融合素材にできます。\n「光と闇の戦士カオス・ソルジャー」",
  "tags": [
    "モンスター"
  ],
  "mentionedCards": [
    22578,
    22976,
    22977
  ]
}
