{
  "fid": 6215,
  "title": "フィールドの魔法・罠カードを破壊する「超重忍者サルト－B」のモンスター効果の処理時に、自分の墓地に魔法・罠カードが存在する場合、処理はどうなりますか？",
  "question": "自分の魔法＆罠ゾーンにセットされたカードが2枚存在し、自分の墓地に魔法・罠カードが1枚もない状況で、自分は「<a href=\"faq_search.action?ope=4&cid=12632\">超重忍者サルト－B</a>」の『②：１ターンに１度、自分の墓地に魔法・罠カードが存在しない場合、フィールドの魔法･罠カード１枚を対象として発動できる。そのカードを破壊し、相手に５００ダメージを与える。この効果は相手ターンでも発動できる』モンスター効果を発動しました。\n\nその発動にチェーンして相手が「<a href=\"faq_search.action?ope=4&cid=12175\">ツインツイスター</a>」を発動し、自分の魔法＆罠ゾーンのカード2枚が破壊され墓地へ送られた場合、「<a href=\"faq_search.action?ope=4&cid=12632\">超重忍者サルト－B</a>」のモンスター効果の処理はどうなりますか？",
  "answer": "質問の状況のように、フィールドの魔法・罠カードを破壊する「<a href=\"faq_search.action?ope=4&cid=12632\">超重忍者サルト－B</a>」のモンスター効果の処理時に、自分の墓地に魔法・罠カードが存在する場合でも、『そのカードを破壊し、相手に５００ダメージを与える』処理は通常通り適用されます。",
  "date": "2017-03-24"
}
