{
  "fid": 7251,
  "databaseDate": "2017-09-21",
  "title": "「リヴェンデット・ボーン」の効果で、手札の「リヴェンデット・スレイヤー」をリリースし、その「リヴェンデット・スレイヤー」を墓地から儀式召喚できますか？",
  "question": "「リヴェンデット・ボーン」の『①：レベルの合計が儀式召喚するモンスターのレベル以上になるように、自分の手札・フィールドのモンスターをリリース、またはリリースの代わりに自分の墓地のアンデット族モンスターを除外し、自分の手札・墓地から「ヴェンデット」儀式モンスター１体を儀式召喚する』効果によって、手札の「リヴェンデット・スレイヤー」をリリースし、そのリリースし墓地に送られた「リヴェンデット・スレイヤー」を儀式召喚する事はできますか？",
  "answer": "「リヴェンデット・ボーン」は儀式魔法の手順として、自分の手札または自分の墓地に存在する「ヴェンデット」と名のついた儀式モンスター１体を選び、そのモンスターのレベルの合計以上になるように、自分の手札・フィールドのモンスターをリリース、またはリリースの代わりに自分の墓地のアンデット族モンスターを除外して、儀式召喚を行います。\n\nしたがって、手札の「リヴェンデット・スレイヤー」を儀式召喚する事を選ぶのであれば、その「リヴェンデット・スレイヤー」自身をリリースする事はできません。\n（その他の自分の手札または自分フィールドのモンスターリリース、またはリリースの代わりに自分の墓地のアンデット族モンスターを除外して儀式召喚を行う事になります。）",
  "tags": [
    "儀式"
  ],
  "mentionedCards": [
    13208,
    13211
  ]
}
