{
  "fid": 7458,
  "title": "「王宮の鉄壁」の効果でカードを除外できない時に、「抹殺の使徒」等の破壊して除外する効果処理はどのように行いますか?",
  "question": "「<a href=\"faq_search.action?ope=4&cid=7858\">王宮の鉄壁</a>」の効果が適用されている時に、カードを『破壊して除外』する効果である「<a href=\"faq_search.action?ope=4&cid=4963\">抹殺の使徒</a>」や「<a href=\"faq_search.action?ope=4&cid=5400\">奈落の落とし穴</a>」、「<a href=\"faq_search.action?ope=4&cid=6076\">破壊竜ガンドラ</a>」等の効果を発動する事はできますか？\nまた、「<a href=\"faq_search.action?ope=4&cid=4963\">抹殺の使徒</a>」等の発動にチェーンをして「<a href=\"faq_search.action?ope=4&cid=7858\">王宮の鉄壁</a>」を発動した場合、効果処理はどのように行いますか？",
  "answer": "「<a href=\"faq_search.action?ope=4&cid=7858\">王宮の鉄壁</a>」の効果が適用されている時に、「<a href=\"faq_search.action?ope=4&cid=4963\">抹殺の使徒</a>」や「<a href=\"faq_search.action?ope=4&cid=5400\">奈落の落とし穴</a>」、「<a href=\"faq_search.action?ope=4&cid=6076\">破壊竜ガンドラ</a>」等の効果を発動する事はできません。\nまた、チェーンして発動した「<a href=\"faq_search.action?ope=4&cid=7858\">王宮の鉄壁</a>」の効果によって、「<a href=\"faq_search.action?ope=4&cid=4963\">抹殺の使徒</a>」等の効果処理を行う時にカードを除外する事ができない場合、破壊されたカードは除外されず、墓地へ送られます。\nなお、「<a href=\"faq_search.action?ope=4&cid=4963\">抹殺の使徒</a>」の場合、破壊したモンスターがリバースモンスターだった場合でも、デッキの確認は行わずその後の効果処理は行いません。",
  "date": "2017-03-24"
}
