{
  "fid": 8416,
  "title": "「地獄からの使い」の効果が、「スキルドレイン」の効果によって無効化された場合、レベル・攻撃力・守備力はどのようになりますか？",
  "question": "モンスター1体をリリースして召喚した「<a href=\"faq_search.action?ope=4&cid=8183\">地獄からの使い</a>」の、自身の効果によってレベルが5になり、元々の攻撃力・守備力が半分になる効果が、「<a href=\"faq_search.action?ope=4&cid=5740\">スキルドレイン</a>」の効果によって無効化された場合、「<a href=\"faq_search.action?ope=4&cid=8183\">地獄からの使い</a>」のレベル・攻撃力・守備力はどのようになりますか？",
  "answer": "自身の効果によってレベルが5になり、元々の攻撃力・守備力が半分になっている「<a href=\"faq_search.action?ope=4&cid=8183\">地獄からの使い</a>」の効果が、「<a href=\"faq_search.action?ope=4&cid=5740\">スキルドレイン</a>」の効果によって無効化された場合、「<a href=\"faq_search.action?ope=4&cid=8183\">地獄からの使い</a>」のレベルはカードに記載されている7になり、攻撃力・守備力は、テキストに記載された2600・1800となります。\nまた、「<a href=\"faq_search.action?ope=4&cid=8183\">地獄からの使い</a>」のレベル・攻撃力・守備力がテキストに記載された数値になった後に「<a href=\"faq_search.action?ope=4&cid=5740\">スキルドレイン</a>」の効果が適用されなくなった場合でも、再びレベル5になり、元々の攻撃力・守備力の半分の数値に戻る事はありません。",
  "date": "2017-03-24"
}
