{
  "fid": 8439,
  "title": "「オーバー・デッド・ライン」の適用中、「ソウル・チャージ」の効果によって、自分の墓地から植物族モンスターを2体同時に特殊召喚した場合、「オーバー・デッド・ライン」の効果はどのように発動し、処理を行いますか？",
  "question": "自分の魔法＆罠ゾーンに「<a href=\"faq_search.action?ope=4&cid=8218\">オーバー・デッド・ライン</a>」が表側表示で存在しています。\n\nこの状況で、「<a href=\"faq_search.action?ope=4&cid=11159\">ソウル・チャージ</a>」を発動し、自分の墓地から植物族モンスターを2体を同時に特殊召喚した場合、「<a href=\"faq_search.action?ope=4&cid=8218\">オーバー・デッド・ライン</a>」の『このカードがフィールド上に存在する限り、墓地から自分フィールド上に特殊召喚した植物族モンスターの攻撃力は１０００ポイントアップする』効果はどのように発動し、処理を行いますか？",
  "answer": "質問の状況のように、複数体の植物族モンスターが同時に墓地から自分のモンスターゾーンに特殊召喚された場合、「<a href=\"faq_search.action?ope=4&cid=8218\">オーバー・デッド・ライン</a>」の効果は1度のみ発動します。\n\nその発動した1度の処理によって、同時に墓地から自分のモンスターゾーンに特殊召喚された植物族モンスターは全て攻撃力が1000アップする事になります。",
  "date": "2017-03-24"
}
