{
  "fid": 9491,
  "title": "「ヴェルズ・オピオン」が存在する際に、「PSYフレームギア・α」等の効果を発動できますか？",
  "question": "エクシーズ素材を持った「<a href=\"faq_search.action?ope=4&cid=10006\">ヴェルズ・オピオン</a>」が相手のモンスターゾーンに表側表示で存在し、『エクシーズ素材を持っているこのカードがフィールド上に表側表示で存在する限り、お互いにレベル５以上のモンスターを特殊召喚できない』効果が適用されています。\n\nこの状況で、自分は手札の「<a href=\"faq_search.action?ope=4&cid=12068\">PSYフレームギア・α</a>」、「<a href=\"faq_search.action?ope=4&cid=12069\">PSYフレームギア・β</a>」、「<a href=\"faq_search.action?ope=4&cid=12070\">PSYフレームギア・γ</a>」、「<a href=\"faq_search.action?ope=4&cid=12071\">PSYフレームギア・δ</a>」、「<a href=\"faq_search.action?ope=4&cid=12072\">PSYフレームギア・ε</a>」の効果を発動する事はできますか？",
  "answer": "質問の状況の場合、「<a href=\"faq_search.action?ope=4&cid=10006\">ヴェルズ・オピオン</a>」の効果が適用されてれおり、レベル6のモンスターである「<a href=\"faq_search.action?ope=4&cid=12067\">PSYフレーム・ドライバー</a>」を特殊召喚する事ができず、「<a href=\"faq_search.action?ope=4&cid=12068\">PSYフレームギア・α</a>」等は処理を行う事ができません。\n\nしたがって、この場合、自分は手札の「<a href=\"faq_search.action?ope=4&cid=12068\">PSYフレームギア・α</a>」等の効果を発動する事自体ができません。",
  "date": "2017-03-24"
}
