{
  "fid": 9569,
  "title": "「アマゾネスの剣士」や「ディメンション・ウォール」の効果で自分が戦闘ダメージを受ける場合、「体力増強剤スーパーZ」を発動できますか？",
  "question": "「<a href=\"faq_search.action?ope=4&cid=5284\">アマゾネスの剣士</a>」や「<a href=\"faq_search.action?ope=4&cid=6448\">ディメンション・ウォール</a>」の効果によって自分が2000以上の戦闘ダメージを受ける場合、「<a href=\"faq_search.action?ope=4&cid=5403\">体力増強剤スーパーZ</a>」を発動する事はできますか？",
  "answer": "「<a href=\"faq_search.action?ope=4&cid=5284\">アマゾネスの剣士</a>」や「<a href=\"faq_search.action?ope=4&cid=6448\">ディメンション・ウォール</a>」の効果が適用される事によって、結果的に自分が2000以上の戦闘ダメージを受ける場合には、そのダメージ計算時に「<a href=\"faq_search.action?ope=4&cid=5403\">体力増強剤スーパーZ</a>」を発動する事ができます。",
  "date": "2017-03-24"
}
