{
  "fid": 9619,
  "title": "「The tyrant NEPTUNE」の攻撃力は、攻撃力と守備力の合計した数値になりますか？",
  "question": "「<a href=\"faq_search.action?ope=4&cid=8733\">The tyrant NEPTUNE</a>」の攻撃力・守備力がアップする場合、リリースしたモンスターの、どの数値を合計して攻撃力・守備力をアップしますか？\n例1）\n「<a href=\"faq_search.action?ope=4&cid=4054\">クリッター</a>」（攻撃力1000・守備力600）1体をリリースしてアドバンス召喚した場合、「<a href=\"faq_search.action?ope=4&cid=8733\">The tyrant NEPTUNE</a>」の攻撃力・守備力は、それぞれ1600アップしますか？\nそれとも、攻撃力が1000、守備力が600と、それぞれアップしますか？\n例2）\n「<a href=\"faq_search.action?ope=4&cid=4054\">クリッター</a>」（攻撃力1000・守備力600）と、「<a href=\"faq_search.action?ope=4&cid=6821\">光と闇の竜</a>」（攻撃力2800・守備力2400）の2体をリリースしてアドバンス召喚した場合、「<a href=\"faq_search.action?ope=4&cid=8733\">The tyrant NEPTUNE</a>」の攻撃力・守備力は、それぞれいくつになりますか？",
  "answer": "「<a href=\"faq_search.action?ope=4&cid=8733\">The tyrant NEPTUNE</a>」をアドバンス召喚した際に、攻撃力・守備力がアップする場合、攻撃力はリリースしたモンスターの攻撃力を合計した数値、守備力はリリースしたモンスターの守備力を合計した数値分アップします。\nよって、例1のように、「<a href=\"faq_search.action?ope=4&cid=4054\">クリッター</a>」（攻撃力1000・守備力600）1体をリリースしてアドバンス召喚した場合、「<a href=\"faq_search.action?ope=4&cid=8733\">The tyrant NEPTUNE</a>」の攻撃力は1000、守備力は600になります。\nまた、例2のように、「<a href=\"faq_search.action?ope=4&cid=4054\">クリッター</a>」と、「<a href=\"faq_search.action?ope=4&cid=6821\">光と闇の竜</a>」（攻撃力2800・守備力2400）の2体をリリースしてアドバンス召喚した場合、「<a href=\"faq_search.action?ope=4&cid=8733\">The tyrant NEPTUNE</a>」の攻撃力は3800、守備力は3000になります。",
  "date": "2017-03-24"
}
