{
  "fid": 9790,
  "databaseDate": "2017-03-24",
  "title": "「アーティファクトの解放」の効果処理時に、対象の「アーティファクト」と名のついたモンスター2体のうち、1体が裏側守備表示になっている場合、どうなりますか？",
  "question": "「アーティファクト－ヴァジュラ」と「アーティファクト－デスサイズ」の2体を対象として「アーティファクトの解放」を発動しました。\n\nその発動にチェーンして、「月の書」が発動し、「アーティファクト－ヴァジュラ」が裏側守備表示になった場合、「アーティファクトの解放」の『選択したモンスター２体のみを素材としてエクシーズモンスター１体をエクシーズ召喚する。このカードを発動したターン、「アーティファクト」と名のついたモンスター以外の自分フィールド上のモンスターは攻撃できない』処理はどうなりますか？",
  "answer": "「アーティファクトの解放」の対象として選択した2体のモンスターのうち、1体が裏側守備表示になっている場合、『選択したモンスター２体のみを素材としてエクシーズモンスター１体をエクシーズ召喚する』事はできません。選択したモンスター2体はそのままモンスターゾーンに残ります。\n\nなお、その場合でも、『このカードを発動したターン、「アーティファクト」と名のついたモンスター以外の自分フィールド上のモンスターは攻撃できない』は適用されます。",
  "tags": [
    "チェーン"
  ],
  "mentionedCards": [
    11090
  ]
}
