{
  "fid": 9930,
  "title": "「<<11093>>」の効果が適用されたモンスターが、ペンデュラムモンスターを戦闘で破壊した場合、処理はどうなりますか？",
  "question": "「<<11093>>」の効果が適用された「<<10784>>」で、相手の「<<11210>>」を戦闘で破壊しました。\n\nこの場合、『このターン選択したモンスターが、そのモンスターの元々の攻撃力以上の攻撃力を持つモンスターを戦闘によって破壊した場合、破壊したそのモンスターを除外し、さらにその同名モンスターを相手の手札・デッキ・エクストラデッキ・墓地から全て除外する』処理はどうなりますか？",
  "answer": "質問の状況のように、「<<11093>>」の効果が適用された「<<10784>>」で攻撃し、「<<11210>>」を戦闘で破壊した場合、「<<11210>>」はペンデュラムモンスターですので戦闘で破壊された際に墓地へは送られず、エクストラデッキに表側表示で加わります。\n\nこの場合、戦闘で破壊したモンスターを「<<11093>>」の効果によって墓地から除外する事ができませんので、『さらにその同名モンスターを相手の手札・デッキ・エクストラデッキ・墓地から全て除外する』処理も適用する事ができません。",
  "date": "2017-03-24"
}
